Pytorch03ZhongwenWendangHeJiaocheng/README.md
Pytorch03ZhongwenWendangHeJiaocheng/__init__.py
Pytorch03ZhongwenWendangHeJiaocheng/__main__.py
Pytorch03ZhongwenWendangHeJiaocheng/file.epub
Pytorch03ZhongwenWendangHeJiaocheng/index.html
Pytorch03ZhongwenWendangHeJiaocheng/css/__init__.py
Pytorch03ZhongwenWendangHeJiaocheng/css/annotations.css
Pytorch03ZhongwenWendangHeJiaocheng/css/main.css
Pytorch03ZhongwenWendangHeJiaocheng/css/normalize.css
Pytorch03ZhongwenWendangHeJiaocheng/css/popup.css
Pytorch03ZhongwenWendangHeJiaocheng/font/__init__.py
Pytorch03ZhongwenWendangHeJiaocheng/font/fontello.eot
Pytorch03ZhongwenWendangHeJiaocheng/font/fontello.svg
Pytorch03ZhongwenWendangHeJiaocheng/font/fontello.ttf
Pytorch03ZhongwenWendangHeJiaocheng/font/fontello.woff
Pytorch03ZhongwenWendangHeJiaocheng/img/__init__.py
Pytorch03ZhongwenWendangHeJiaocheng/img/annotator-glyph-sprite.png
Pytorch03ZhongwenWendangHeJiaocheng/img/annotator-icon-sprite.png
Pytorch03ZhongwenWendangHeJiaocheng/img/apple-touch-icon.png
Pytorch03ZhongwenWendangHeJiaocheng/img/cancelfullscreen.png
Pytorch03ZhongwenWendangHeJiaocheng/img/close.png
Pytorch03ZhongwenWendangHeJiaocheng/img/fullscreen.png
Pytorch03ZhongwenWendangHeJiaocheng/img/loader.gif
Pytorch03ZhongwenWendangHeJiaocheng/img/menu-icon.png
Pytorch03ZhongwenWendangHeJiaocheng/img/save.png
Pytorch03ZhongwenWendangHeJiaocheng/img/saved.png
Pytorch03ZhongwenWendangHeJiaocheng/img/settings-s.png
Pytorch03ZhongwenWendangHeJiaocheng/img/settings.png
Pytorch03ZhongwenWendangHeJiaocheng/img/star.png
Pytorch03ZhongwenWendangHeJiaocheng/js/__init__.py
Pytorch03ZhongwenWendangHeJiaocheng/js/epub.js
Pytorch03ZhongwenWendangHeJiaocheng/js/epub.min.js
Pytorch03ZhongwenWendangHeJiaocheng/js/epub.min.map
Pytorch03ZhongwenWendangHeJiaocheng/js/hooks.min.js
Pytorch03ZhongwenWendangHeJiaocheng/js/hooks.min.map
Pytorch03ZhongwenWendangHeJiaocheng/js/reader.js
Pytorch03ZhongwenWendangHeJiaocheng/js/reader.js.map
Pytorch03ZhongwenWendangHeJiaocheng/js/reader.min.js
pytorch_0_3_zhongwen_wendang_he_jiaocheng-2024.3.4.0.dist-info/METADATA
pytorch_0_3_zhongwen_wendang_he_jiaocheng-2024.3.4.0.dist-info/WHEEL
pytorch_0_3_zhongwen_wendang_he_jiaocheng-2024.3.4.0.dist-info/entry_points.txt
pytorch_0_3_zhongwen_wendang_he_jiaocheng-2024.3.4.0.dist-info/top_level.txt
pytorch_0_3_zhongwen_wendang_he_jiaocheng-2024.3.4.0.dist-info/RECORD
